toolbox/__init__.py
toolbox/constitutes/__init__.py
toolbox/constitutes/constitute_adjustment.py
toolbox/db/__init__.py
toolbox/db/settings.py
toolbox/db/api/__init__.py
toolbox/db/api/sql_connection.py
toolbox/db/read/__init__.py
toolbox/db/read/db_functions.py
toolbox/db/read/etf_universe.py
toolbox/db/read/query_constructor.py
toolbox/db/testing/__init__.py
toolbox/db/testing/portal.py
toolbox/db/write/__init__.py
toolbox/db/write/create_tables.py
toolbox/db/write/make_universes.py
toolbox/db/write/rebuild.py
toolbox/ml/__init__.py
toolbox/ml/ml_factor_calculation.py
toolbox/ml/model_wrapper.py
toolbox/tests/__init__.py
toolbox/tests/constitute_adjustment_test.py
toolbox/tests/ml_factor_calculation_test.py
toolbox/utils/IC.py
toolbox/utils/__init__.py
toolbox/utils/format_data_alphalens.py
toolbox/utils/handle_data.py
toolbox/utils/slice_holder.py
factor_toolbox-1.1.4.dist-info/LICENSE.txt
factor_toolbox-1.1.4.dist-info/METADATA
factor_toolbox-1.1.4.dist-info/WHEEL
factor_toolbox-1.1.4.dist-info/top_level.txt
factor_toolbox-1.1.4.dist-info/RECORD
