Metadata-Version: 2.1
Name: factor-toolbox
Version: 1.1.4
Summary: A simple toolbox to aid in the exploration of potential alpha sources.
Home-page: https://github.com/Alexd14/factor-toolbox
Author: Alex
Author-email: 
License: MIT
Download-URL: https://github.com/Alexd14/toolbox/archive/refs/tags/v1.1.4.tar.gz
Keywords: factor,equity factor
Platform: UNKNOWN
Classifier: License :: OSI Approved :: MIT License
Classifier: Programming Language :: Python :: 3.7
Classifier: Programming Language :: Python :: 3.8
Classifier: Programming Language :: Python :: 3.9
License-File: LICENSE.txt
Requires-Dist: pandas
Requires-Dist: pandas-market-calendars
Requires-Dist: tqdm
Requires-Dist: numpy
Requires-Dist: duckdb
